dataclasses_codec/__init__.py
dataclasses_codec/core.py
dataclasses_codec/errors.py
dataclasses_codec/py.typed
dataclasses_codec/codecs/__init__.py
dataclasses_codec/codecs/json.py
dataclasses_codec-1.1.0.dist-info/METADATA
dataclasses_codec-1.1.0.dist-info/WHEEL
dataclasses_codec-1.1.0.dist-info/licenses/LICENSE
dataclasses_codec-1.1.0.dist-info/RECORD
