Metadata-Version: 2.4
Name: dataclasses-codec
Version: 1.1.0
Summary: Simple Python dataclass serialization package with no dependencies
Project-URL: Homepage, https://github.com/stupid-simple/dataclasses-codec
Project-URL: Repository, https://github.com/stupid-simple/dataclasses-codec
Project-URL: Issues, https://github.com/stupid-simple/dataclasses-codec/issues
Project-URL: Documentation, https://github.com/stupid-simple/dataclasses-codec#readme
Author-email: i-segura <github@m.isu101.com>
License-Expression: MIT
License-File: LICENSE
Keywords: codec,dataclass,decoder,encoder,json,serialization
Classifier: Development Status :: 5 - Production/Stable
Classifier: Intended Audience :: Developers
Classifier: License :: OSI Approved :: MIT License
Classifier: Programming Language :: Python :: 3
Classifier: Programming Language :: Python :: 3 :: Only
Classifier: Programming Language :: Python :: 3.10
Classifier: Programming Language :: Python :: 3.11
Classifier: Programming Language :: Python :: 3.12
Classifier: Programming Language :: Python :: 3.13
Classifier: Programming Language :: Python :: 3.14
Classifier: Topic :: Software Development :: Libraries :: Python Modules
Classifier: Typing :: Typed
Requires-Python: >=3.10
